hybrid_utils/__init__.py
hybrid_utils/all.py
hybrid_utils/base64.py
hybrid_utils/textcolor.py
hybrid_utils/version.py
hybrid_utils-0.0.2.dist-info/METADATA
hybrid_utils-0.0.2.dist-info/WHEEL
hybrid_utils-0.0.2.dist-info/top_level.txt
hybrid_utils-0.0.2.dist-info/RECORD
