Metadata-Version: 2.4
Name: hybrid_utils
Version: 0.0.2
Summary: Use Utils For a Bunch Of Stuff!
Author-email: SH_Dev <glock.96.beamed@gmail.com>
Requires-Python: >=3.7
Dynamic: requires-python
